fred/categories.py
fred/client.py
fred/releases.py
fred/series.py
fred/session.py
fred/sources.py
fred/tags.py
federal_reserve_python_api-0.1.0.dist-info/LICENSE
federal_reserve_python_api-0.1.0.dist-info/METADATA
federal_reserve_python_api-0.1.0.dist-info/WHEEL
federal_reserve_python_api-0.1.0.dist-info/top_level.txt
federal_reserve_python_api-0.1.0.dist-info/RECORD
